{
  "fornecedores": [
    {
      "id": "33d1",
      "nome": "Fornecedor de pesas usadas",
      "descricao": "Fornecedora de pesas usadas para maquinário.",
      "contato": [
        {
          "nome": "Geovane Hartmann",
          "telefone": "51999999999",
          "prioritario": true
        }
      ],
      "endereco": {
        "cep": "93615320",
        "logradouro": "Rua do Fornecedor",
        "numero": "1234",
        "cidade": "Novo Hamburgo",
        "estado": "RS",
        "bairro": "BAIRRO DO FORN",
        "referencia": "CASA DA ESQUINA DO FORNECEDOR"
      }
    },
    {
      "id": "d224",
      "nome": "DBC Company",
      "descricao": "Fornecedora de desenvolvedores",
      "contato": [
        {
          "nome": "Jonas Silva",
          "telefone": "51989072379",
          "prioritario": true
        },
        {
          "nome": "ALTEREI",
          "telefone": "5198",
          "prioritario": false
        }
      ],
      "endereco": {
        "cep": "93615320",
        "logradouro": "Rua Luiz Gama",
        "numero": "1234",
        "cidade": "Estância Velha",
        "estado": "RS",
        "bairro": "Lira",
        "referencia": "JJJJJJJJ"
      }
    },
    {
      "id": "0c61",
      "nome": "VExpenses Despesas Corporativas",
      "descricao": "Fornecedor de despesas corporativas número um do mercado.",
      "contato": [
        {
          "nome": "João Fonseca",
          "telefone": "51989072379",
          "prioritario": true
        }
      ],
      "endereco": {
        "cep": "90250590",
        "logradouro": "Avenida Padre Leopoldo Brentano",
        "numero": "1663",
        "cidade": "Porto Alegre",
        "estado": "RS",
        "bairro": "Farrapos",
        "referencia": "Arena do Grêmio"
      }
    }
  ],
  "status": [
    {
      "id": "1",
      "tipo": "Solicitado"
    },
    {
      "id": "2",
      "tipo": "Em produção"
    },
    {
      "id": "3",
      "tipo": "Finalizado"
    }
  ]
}